integra_bridge/__init__.py
integra_bridge/adapters/__init__.py
integra_bridge/adapters/base_adapter.py
integra_bridge/adapters/base_input_connector.py
integra_bridge/adapters/base_processor.py
integra_bridge/adapters/multiprocess_connector.py
integra_bridge/adapters/output_connector.py
integra_bridge/adapters/single_mode_connector.py
integra_bridge/api_router.py
integra_bridge/bridge.py
integra_bridge/common/__init__.py
integra_bridge/common/dependency_manager.py
integra_bridge/common/enums.py
integra_bridge/common/settings.py
integra_bridge/dto/__init__.py
integra_bridge/dto/body.py
integra_bridge/dto/connector_to_block_view.py
integra_bridge/dto/exchange.py
integra_bridge/dto/parameter.py
integra_bridge/dto/redeploy.py
integra_bridge/dto/responces/__init__.py
integra_bridge/dto/responces/external_service.py
integra_bridge/dto/responces/validation.py
integra_bridge/dto/skeletons/__init__.py
integra_bridge/dto/skeletons/connector.py
integra_bridge/dto/skeletons/processor.py
integra_bridge/dto/views/__init__.py
integra_bridge/dto/views/connector_view.py
integra_bridge/dto/views/processor_view.py
integra_bridge/entity/__init__.py
integra_bridge/entity/block.py
integra_bridge/entity/connector.py
integra_bridge/entity/output_status.py
integra_bridge/entity/processed_components.py
integra_bridge/entity/processor.py
integra_bridge/patterns/__init__.py
integra_bridge/patterns/singleton.py
integra_bridge/routers/__init__.py
integra_bridge/routers/v1/__init__.py
integra_bridge/routers/v1/base.py
integra_bridge/routers/v1/configuration.py
integra_bridge/routers/v1/connector.py
integra_bridge/routers/v1/processor.py
integra_bridge/routers/v1/service.py
integra_bridge/services/__init__.py
integra_bridge/services/configuration.py
integra_bridge/services/connector.py
integra_bridge/services/processor.py
integra_bridge/utils/__init__.py
integra_bridge/utils/mapping_data.py
integra_bridge-0.2.5.dist-info/METADATA
integra_bridge-0.2.5.dist-info/WHEEL
integra_bridge-0.2.5.dist-info/RECORD
